astartool/__init__.py
astartool/common.py
astartool/data_structure/__init__.py
astartool/data_structure/bisect.py
astartool/data_structure/heap.py
astartool/data_structure/keymap.py
astartool/data_structure/lazymap.py
astartool/data_structure/linked_list.py
astartool/data_structure/mergemap.py
astartool/data_structure/queue.py
astartool/data_structure/union_find.py
astartool/error/__init__.py
astartool/error/_error.py
astartool/error/lazydict_error.py
astartool/exception/__init__.py
astartool/exception/_exception.py
astartool/exception/file_exception.py
astartool/file/__init__.py
astartool/file/compresshelper.py
astartool/file/downloadhelper.py
astartool/file/excelhelper.py
astartool/file/filehelper.py
astartool/file/imagehelper.py
astartool/number/__init__.py
astartool/number/_number.py
astartool/project/__init__.py
astartool/project/_decorators.py
astartool/project/_log.py
astartool/project/_platform.py
astartool/project/_profiler.py
astartool/project/_project.py
astartool/project/_time.py
astartool/random/__init__.py
astartool/random/_random.py
astartool/setuptool/__init__.py
astartool/setuptool/_tool.py
astartool/setuptool/_version.py
astartool/string/__init__.py
astartool/string/_string.py
astartool/string/password_check.py
astartool-0.1.4.dist-info/licenses/LICENSE
astartool-0.1.4.dist-info/METADATA
astartool-0.1.4.dist-info/WHEEL
astartool-0.1.4.dist-info/top_level.txt
astartool-0.1.4.dist-info/RECORD
