Metadata-Version: 2.4
Name: astartool
Version: 0.1.4
Summary: toolkit for python
Home-page: https://gitee.com/hoops/astartool
Author: A.Star
Author-email: astar@snowland.ltd
Maintainer: A.Star
Maintainer-email: astar@snowland.ltd
License: Apache v2.0
Platform: all
Classifier: Operating System :: OS Independent
Classifier: Intended Audience :: Developers
Classifier: Programming Language :: Python
Classifier: Programming Language :: Python :: Implementation
Classifier: Programming Language :: Python :: 3
Classifier: Programming Language :: Python :: 3.6
Classifier: Programming Language :: Python :: 3.7
Classifier: Programming Language :: Python :: 3.8
Classifier: Programming Language :: Python :: 3.9
Classifier: Programming Language :: Python :: 3.10
Classifier: Programming Language :: Python :: 3.11
Classifier: Programming Language :: Python :: 3.12
Classifier: Programming Language :: Python :: 3.13
Classifier: Topic :: Software Development :: Libraries
License-File: LICENSE
Requires-Dist: numpy>=1.0.1
Requires-Dist: snowland-smx>=0.3.1
Requires-Dist: rarfile
Requires-Dist: xlwt
Requires-Dist: pillow
Requires-Dist: six
Requires-Dist: wrapt
Requires-Dist: xlrd
Requires-Dist: scipy>=1.0.1
Dynamic: author
Dynamic: author-email
Dynamic: classifier
Dynamic: description
Dynamic: home-page
Dynamic: license
Dynamic: license-file
Dynamic: maintainer
Dynamic: maintainer-email
Dynamic: platform
Dynamic: requires-dist
Dynamic: summary
